package com.tencent.lbssearch.a.a.b.a;

import com.tencent.lbssearch.a.a.c.a;
import com.tencent.lbssearch.a.a.d.a;
import com.tencent.lbssearch.a.a.d.c;
import com.tencent.lbssearch.a.a.f;
import com.tencent.lbssearch.a.a.w;
import com.tencent.lbssearch.a.a.x;
import java.io.IOException;
import java.sql.Date;
import java.text.DateFormat;
import java.text.SimpleDateFormat;

public final class i extends w<Date> {
  public static final x a = new x() {
      public <T> w<T> a(f param1f, a<T> param1a) {
        if (param1a.a() == Date.class) {
          i i = new i();
        } else {
          param1f = null;
        } 
        return (w<T>)param1f;
      }
    };
  
  private final DateFormat b = new SimpleDateFormat("MMM d, yyyy");
  
  public Date a(a parama) throws IOException {
    // Byte code:
    //   0: aload_0
    //   1: monitorenter
    //   2: aload_1
    //   3: invokevirtual f : ()Lcom/tencent/lbssearch/a/a/d/b;
    //   6: getstatic com/tencent/lbssearch/a/a/d/b.i : Lcom/tencent/lbssearch/a/a/d/b;
    //   9: if_acmpne -> 20
    //   12: aload_1
    //   13: invokevirtual j : ()V
    //   16: aload_0
    //   17: monitorexit
    //   18: aconst_null
    //   19: areturn
    //   20: new java/sql/Date
    //   23: dup
    //   24: aload_0
    //   25: getfield b : Ljava/text/DateFormat;
    //   28: aload_1
    //   29: invokevirtual h : ()Ljava/lang/String;
    //   32: invokevirtual parse : (Ljava/lang/String;)Ljava/util/Date;
    //   35: invokevirtual getTime : ()J
    //   38: invokespecial <init> : (J)V
    //   41: astore_1
    //   42: aload_0
    //   43: monitorexit
    //   44: aload_1
    //   45: areturn
    //   46: astore_2
    //   47: new com/tencent/lbssearch/a/a/t
    //   50: astore_1
    //   51: aload_1
    //   52: aload_2
    //   53: invokespecial <init> : (Ljava/lang/Throwable;)V
    //   56: aload_1
    //   57: athrow
    //   58: astore_1
    //   59: aload_0
    //   60: monitorexit
    //   61: aload_1
    //   62: athrow
    // Exception table:
    //   from	to	target	type
    //   2	16	58	finally
    //   20	42	46	java/text/ParseException
    //   20	42	58	finally
    //   47	58	58	finally
  }
  
  public void a(c paramc, Date paramDate) throws IOException {
    // Byte code:
    //   0: aload_0
    //   1: monitorenter
    //   2: aload_2
    //   3: ifnonnull -> 11
    //   6: aconst_null
    //   7: astore_2
    //   8: goto -> 20
    //   11: aload_0
    //   12: getfield b : Ljava/text/DateFormat;
    //   15: aload_2
    //   16: invokevirtual format : (Ljava/util/Date;)Ljava/lang/String;
    //   19: astore_2
    //   20: aload_1
    //   21: aload_2
    //   22: invokevirtual b : (Ljava/lang/String;)Lcom/tencent/lbssearch/a/a/d/c;
    //   25: pop
    //   26: aload_0
    //   27: monitorexit
    //   28: return
    //   29: astore_1
    //   30: aload_0
    //   31: monitorexit
    //   32: aload_1
    //   33: athrow
    // Exception table:
    //   from	to	target	type
    //   11	20	29	finally
    //   20	26	29	finally
  }
}


/* Location:              F:\何章易\项目文件夹\项目24\va\classes_merge.jar!\com\tencent\lbssearch\a\a\b\a\i.class
 * Java compiler version: 6 (50.0)
 * JD-Core Version:       1.1.3
 */